gadlint/__init__.py
gadlint/cli.py
gadlint/configs/.isort.cfg
gadlint/configs/mypy.ini
gadlint/configs/ruff.toml
gadlint-0.0.3.dist-info/LICENSE
gadlint-0.0.3.dist-info/METADATA
gadlint-0.0.3.dist-info/WHEEL
gadlint-0.0.3.dist-info/entry_points.txt
gadlint-0.0.3.dist-info/top_level.txt
gadlint-0.0.3.dist-info/RECORD
