Metadata-Version: 2.1
Name: gadlint
Version: 0.0.3
Summary: CLI tool that runs isort, ruff, mypy, and radon with built-in configurations.
Home-page: https://github.com/AlexDemure/gadlint
Author: Alexander Grishchenko
Author-email: alexanderdemure@gmail.com
Classifier: Programming Language :: Python :: 3
Classifier: License :: OSI Approved :: MIT License
Classifier: Operating System :: OS Independent
Requires-Python: >=3.8
License-File: LICENSE
Requires-Dist: isort
Requires-Dist: mypy
Requires-Dist: radon
Requires-Dist: ruff
Requires-Dist: typer
